beansofts/__init__.py
beansofts/flasklogger.py
flaskLogTest-0.0.5.dist-info/METADATA
flaskLogTest-0.0.5.dist-info/WHEEL
flaskLogTest-0.0.5.dist-info/top_level.txt
flaskLogTest-0.0.5.dist-info/RECORD
