Metadata-Version: 2.1
Name: flaskLogTest
Version: 0.0.5
Summary: this is a simple flasklogger v=0.0.4
Home-page: UNKNOWN
Author: Me
License: MIT
Platform: UNKNOWN
Requires-Dist: PyJWT (==1.7.1)
Requires-Dist: flask
Requires-Dist: geocoder
Requires-Dist: pika
